{
  "version": "7",
  "dialect": "postgresql",
  "entries": [
    {
      "idx": 0,
      "version": "7",
      "when": 1740650572670,
      "tag": "0000_abandoned_boom_boom",
      "breakpoints": true
    },
    {
      "idx": 1,
      "version": "7",
      "when": 1740651050882,
      "tag": "0001_sharp_white_queen",
      "breakpoints": true
    },
    {
      "idx": 2,
      "version": "7",
      "when": 1740654545149,
      "tag": "0002_aromatic_mentor",
      "breakpoints": true
    }
  ]
}